LICENSE
MANIFEST.in
README.md
setup.cfg
setup.py
versioneer.py
q2_gg2/__init__.py
q2_gg2/_format.py
q2_gg2/_methods.py
q2_gg2/_transformer.py
q2_gg2/_type.py
q2_gg2/_version.py
q2_gg2/plugin_setup.py
q2_gg2/tests/__init__.py
q2_gg2/tests/test_methods.py
q2_greengenes2.egg-info/PKG-INFO
q2_greengenes2.egg-info/SOURCES.txt
q2_greengenes2.egg-info/dependency_links.txt
q2_greengenes2.egg-info/entry_points.txt
q2_greengenes2.egg-info/not-zip-safe
q2_greengenes2.egg-info/requires.txt
q2_greengenes2.egg-info/top_level.txt