Metadata-Version: 1.0
Name: q2-greengenes2
Version: 2024.1
Summary: Support methods for interaction with Greengenes2
Home-page: https://github.com/biocore/q2-greengenes2
Author: UNKNOWN
Author-email: UNKNOWN
License: BSD-3-Clause
Platform: UNKNOWN
